<?xml version="1.0" encoding="UTF-8"?><courseList><course><编号>SE0001</编号><名称>计算机基础</名称><学分>2</学分><老师>王老师</老师><地点>101</地点></course><course><编号>SE0002</编号><名称>操作系统</名称><学分>4</学分><老师>赵老师</老师><地点>102</地点></course><course><编号>SE0003</编号><名称>编译原理</名称><学分>3</学分><老师>钱老师</老师><地点>103</地点></course><course><编号>SE0004</编号><名称>计算机组成原理</名称><学分>4</学分><老师>孙老师</老师><地点>104</地点></course><course><编号>SE0005</编号><名称>C语言</名称><学分>4</学分><老师>李老师</老师><地点>105</地点></course><course><编号>SE0006</编号><名称>JAVA程序设计</名称><学分>4</学分><老师>周老师</老师><地点>106</地点></course><course><编号>SE0007</编号><名称>数据库原理</名称><学分>3</学分><老师>武老师</老师><地点>107</地点></course><course><编号>SE0008</编号><名称>计算机网络</名称><学分>4</学分><老师>陈老师</老师><地点>108</地点></course><course><编号>SE0009</编号><名称>云计算</名称><学分>3</学分><老师>马老师</老师><地点>109</地点></course><course><编号>SE0010</编号><名称>数据结构</名称><学分>3</学分><老师>张老师</老师><地点>110</地点></course></courseList>